src/__init__.py
src/abi/__init__.py
src/function/__init__.py
src/function/eth.py
src/function/index.py
src/function/solana.py
src/provider/__init__.py
src/provider/wallet.py
src/util/__init__.py
src/util/index.py
multichain.crypto.wallet-0.0.1.dist-info/METADATA
multichain.crypto.wallet-0.0.1.dist-info/WHEEL
multichain.crypto.wallet-0.0.1.dist-info/top_level.txt
multichain.crypto.wallet-0.0.1.dist-info/RECORD
